[
  {
    "id": "72476",
    "name": "Bernd Leno",
    "url": "https://www.transfermarkt.com/bernd-leno/profil/spieler/72476",
    "imageUrl": "https://img.a.transfermarkt.technology/portrait/header/72476-1642711733.jpg?lm=1",
    "localImagePath": "public/images/players/fc-fulham/72476.jpg",
    "team": "Fulham FC",
    "teamSlug": "fc-fulham",
    "dateOfBirth": "04/03/1992",
    "age": 33,
    "placeOfBirth": "Bietigheim-Bissingen",
    "citizenship": [
      "Germany"
    ],
    "height": "1,90 m",
    "position": "Goalkeeper",
    "foot": "right",
    "currentClub": "Fulham FC",
    "joined": "02/08/2022",
    "contractExpires": "30/06/2027",
    "marketValue": "€10.00m",
    "shirtNumber": "1",
    "agent": "fair-sport GmbH",
    "internationalTeam": null,
    "internationalCaps": null,
    "internationalGoals": null
  },
  {
    "id": "127181",
    "name": "Benjamin Lecomte",
    "url": "https://www.transfermarkt.com/benjamin-lecomte/profil/spieler/127181",
    "imageUrl": "https://img.a.transfermarkt.technology/portrait/header/127181-1702663657.JPG?lm=1",
    "localImagePath": "public/images/players/fc-fulham/127181.jpg",
    "team": "Fulham FC",
    "teamSlug": "fc-fulham",
    "dateOfBirth": "26/04/1991",
    "age": 34,
    "placeOfBirth": "Paris",
    "citizenship": [
      "France"
    ],
    "height": "1,86 m",
    "position": "Goalkeeper",
    "foot": "left",
    "currentClub": "Fulham FC",
    "joined": "26/07/2025",
    "contractExpires": "30/06/2027",
    "marketValue": "€1.50m",
    "shirtNumber": "23",
    "agent": "YSI Football",
    "internationalTeam": null,
    "internationalCaps": null,
    "internationalGoals": null
  },
  {
    "id": "461883",
    "name": "Calvin Bassey",
    "url": "https://www.transfermarkt.com/calvin-bassey/profil/spieler/461883",
    "imageUrl": "https://img.a.transfermarkt.technology/portrait/header/461883-1662989506.jpg?lm=1",
    "localImagePath": "public/images/players/fc-fulham/461883.jpg",
    "team": "Fulham FC",
    "teamSlug": "fc-fulham",
    "dateOfBirth": "31/12/1999",
    "age": 25,
    "placeOfBirth": "Aosta",
    "citizenship": [
      "Nigeria"
    ],
    "height": "1,85 m",
    "position": "Centre-Back",
    "foot": "left",
    "currentClub": "Fulham FC",
    "joined": "28/07/2023",
    "contractExpires": "30/06/2027",
    "marketValue": "€28.00m",
    "shirtNumber": "3",
    "agent": "Unique Sports Group",
    "internationalTeam": "Nigeria",
    "internationalCaps": 37,
    "internationalGoals": 0
  },
  {
    "id": "260827",
    "name": "Joachim Andersen",
    "url": "https://www.transfermarkt.com/joachim-andersen/profil/spieler/260827",
    "imageUrl": "https://img.a.transfermarkt.technology/portrait/header/260827-1668183482.jpg?lm=1",
    "localImagePath": "public/images/players/fc-fulham/260827.jpg",
    "team": "Fulham FC",
    "teamSlug": "fc-fulham",
    "dateOfBirth": "31/05/1996",
    "age": 29,
    "placeOfBirth": "Frederiksberg",
    "citizenship": [
      "Denmark"
    ],
    "height": "1,92 m",
    "position": "Centre-Back",
    "foot": "right",
    "currentClub": "Fulham FC",
    "joined": "23/08/2024",
    "contractExpires": "30/06/2029",
    "marketValue": "€27.00m",
    "shirtNumber": "5",
    "agent": "SEG",
    "internationalTeam": "Denmark",
    "internationalCaps": 48,
    "internationalGoals": 1
  },
  {
    "id": "272622",
    "name": "Issa Diop",
    "url": "https://www.transfermarkt.com/issa-diop/profil/spieler/272622",
    "imageUrl": "https://img.a.transfermarkt.technology/portrait/header/272622-1660565295.jpg?lm=1",
    "localImagePath": "public/images/players/fc-fulham/272622.jpg",
    "team": "Fulham FC",
    "teamSlug": "fc-fulham",
    "dateOfBirth": "09/01/1997",
    "age": 28,
    "placeOfBirth": "Toulouse",
    "citizenship": [
      "France"
    ],
    "height": "1,94 m",
    "position": "Centre-Back",
    "foot": "right",
    "currentClub": "Fulham FC",
    "joined": "10/08/2022",
    "contractExpires": "30/06/2027",
    "marketValue": "€12.00m",
    "shirtNumber": "31",
    "agent": null,
    "internationalTeam": null,
    "internationalCaps": null,
    "internationalGoals": null
  },
  {
    "id": "494880",
    "name": "Jorge Cuenca",
    "url": "https://www.transfermarkt.com/jorge-cuenca/profil/spieler/494880",
    "imageUrl": "https://img.a.transfermarkt.technology/portrait/header/494880-1737920132.jpg?lm=1",
    "localImagePath": "public/images/players/fc-fulham/494880.jpg",
    "team": "Fulham FC",
    "teamSlug": "fc-fulham",
    "dateOfBirth": "17/11/1999",
    "age": 26,
    "placeOfBirth": "Madrid",
    "citizenship": [
      "Spain"
    ],
    "height": "1,90 m",
    "position": "Centre-Back",
    "foot": "left",
    "currentClub": "Fulham FC",
    "joined": "03/08/2024",
    "contractExpires": "30/06/2028",
    "marketValue": "€5.00m",
    "shirtNumber": "15",
    "agent": "InterStarDeporte",
    "internationalTeam": null,
    "internationalCaps": null,
    "internationalGoals": null
  },
  {
    "id": "349701",
    "name": "Antonee Robinson Antonee Robinson",
    "url": "https://www.transfermarkt.com/antonee-robinson/profil/spieler/349701",
    "imageUrl": "https://img.a.transfermarkt.technology/portrait/header/349701-1703926612.jpg?lm=1",
    "localImagePath": "public/images/players/fc-fulham/349701.jpg",
    "team": "Fulham FC",
    "teamSlug": "fc-fulham",
    "dateOfBirth": "08/08/1997",
    "age": 28,
    "placeOfBirth": "Milton Keynes",
    "citizenship": [
      "United States"
    ],
    "height": "1,83 m",
    "position": "Left-Back",
    "foot": "left",
    "currentClub": "Fulham FC",
    "joined": "20/08/2020",
    "contractExpires": "30/06/2028",
    "marketValue": "€35.00m",
    "shirtNumber": "33",
    "agent": "Wasserman",
    "internationalTeam": null,
    "internationalCaps": null,
    "internationalGoals": null
  },
  {
    "id": "392775",
    "name": "Ryan Sessegnon",
    "url": "https://www.transfermarkt.com/ryan-sessegnon/profil/spieler/392775",
    "imageUrl": "https://img.a.transfermarkt.technology/portrait/header/392775-1722077271.jpg?lm=1",
    "localImagePath": "public/images/players/fc-fulham/392775.jpg",
    "team": "Fulham FC",
    "teamSlug": "fc-fulham",
    "dateOfBirth": "18/05/2000",
    "age": 25,
    "placeOfBirth": "London",
    "citizenship": [
      "England"
    ],
    "height": "1,78 m",
    "position": "Left-Back",
    "foot": "left",
    "currentClub": "Fulham FC",
    "joined": "26/07/2024",
    "contractExpires": "30/06/2026",
    "marketValue": "€18.00m",
    "shirtNumber": "30",
    "agent": "Unique Sports Group",
    "internationalTeam": null,
    "internationalCaps": null,
    "internationalGoals": null
  },
  {
    "id": "206746",
    "name": "Kenny Tete",
    "url": "https://www.transfermarkt.com/kenny-tete/profil/spieler/206746",
    "imageUrl": "https://img.a.transfermarkt.technology/portrait/header/206746-1746645948.jpg?lm=1",
    "localImagePath": "public/images/players/fc-fulham/206746.jpg",
    "team": "Fulham FC",
    "teamSlug": "fc-fulham",
    "dateOfBirth": "09/10/1995",
    "age": 30,
    "placeOfBirth": "Amsterdam",
    "citizenship": [
      "Netherlands"
    ],
    "height": "1,80 m",
    "position": "Right-Back",
    "foot": "right",
    "currentClub": "Fulham FC",
    "joined": "10/09/2020",
    "contractExpires": "30/06/2028",
    "marketValue": "€13.00m",
    "shirtNumber": "2",
    "agent": "HCM Sports",
    "internationalTeam": null,
    "internationalCaps": null,
    "internationalGoals": null
  },
  {
    "id": "262226",
    "name": "Timothy Castagne",
    "url": "https://www.transfermarkt.com/timothy-castagne/profil/spieler/262226",
    "imageUrl": "https://img.a.transfermarkt.technology/portrait/header/262226-1762354618.jpg?lm=1",
    "localImagePath": "public/images/players/fc-fulham/262226.jpg",
    "team": "Fulham FC",
    "teamSlug": "fc-fulham",
    "dateOfBirth": "05/12/1995",
    "age": 29,
    "placeOfBirth": "Arlon",
    "citizenship": [
      "Belgium"
    ],
    "height": "1,85 m",
    "position": "Right-Back",
    "foot": "right",
    "currentClub": "Fulham FC",
    "joined": "29/08/2023",
    "contractExpires": "30/06/2027",
    "marketValue": "€13.00m",
    "shirtNumber": "21",
    "agent": "SENERGIES BV",
    "internationalTeam": "Belgium",
    "internationalCaps": 60,
    "internationalGoals": 2
  },
  {
    "id": "333014",
    "name": "Sander Berge",
    "url": "https://www.transfermarkt.com/sander-berge/profil/spieler/333014",
    "imageUrl": "https://img.a.transfermarkt.technology/portrait/header/333014-1679676693.jpg?lm=1",
    "localImagePath": "public/images/players/fc-fulham/333014.jpg",
    "team": "Fulham FC",
    "teamSlug": "fc-fulham",
    "dateOfBirth": "14/02/1998",
    "age": 27,
    "placeOfBirth": "Bærum",
    "citizenship": [
      "Norway"
    ],
    "height": "1,95 m",
    "position": "Defensive Midfield",
    "foot": "right",
    "currentClub": "Fulham FC",
    "joined": "22/08/2024",
    "contractExpires": "30/06/2029",
    "marketValue": "€25.00m",
    "shirtNumber": "16",
    "agent": "Keypass AS",
    "internationalTeam": "Norway",
    "internationalCaps": 62,
    "internationalGoals": 1
  },
  {
    "id": "245056",
    "name": "Saša Lukić",
    "url": "https://www.transfermarkt.com/sasa-lukic/profil/spieler/245056",
    "imageUrl": "https://img.a.transfermarkt.technology/portrait/header/245056-1746645290.jpg?lm=1",
    "localImagePath": "public/images/players/fc-fulham/245056.jpg",
    "team": "Fulham FC",
    "teamSlug": "fc-fulham",
    "dateOfBirth": "13/08/1996",
    "age": 29,
    "placeOfBirth": null,
    "citizenship": [
      "Serbia"
    ],
    "height": "1,82 m",
    "position": "Central Midfield",
    "foot": "right",
    "currentClub": "Fulham FC",
    "joined": "31/01/2023",
    "contractExpires": "30/06/2027",
    "marketValue": "€14.00m",
    "shirtNumber": "20",
    "agent": "Friends & Football",
    "internationalTeam": "Serbia",
    "internationalCaps": 60,
    "internationalGoals": 2
  },
  {
    "id": "1011131",
    "name": "Josh King",
    "url": "https://www.transfermarkt.com/josh-king/profil/spieler/1011131",
    "imageUrl": "https://img.a.transfermarkt.technology/portrait/header/1011131-1752773470.jpg?lm=1",
    "localImagePath": "public/images/players/fc-fulham/1011131.jpg",
    "team": "Fulham FC",
    "teamSlug": "fc-fulham",
    "dateOfBirth": "03/01/2007",
    "age": 18,
    "placeOfBirth": "London",
    "citizenship": [
      "England"
    ],
    "height": "1,73 m",
    "position": "Central Midfield",
    "foot": "right",
    "currentClub": "Fulham FC",
    "joined": "01/07/2024",
    "contractExpires": "30/06/2029",
    "marketValue": "€10.00m",
    "shirtNumber": "24",
    "agent": "Wasserman",
    "internationalTeam": null,
    "internationalCaps": null,
    "internationalGoals": null
  },
  {
    "id": "226973",
    "name": "Harrison Reed",
    "url": "https://www.transfermarkt.com/harrison-reed/profil/spieler/226973",
    "imageUrl": "https://img.a.transfermarkt.technology/portrait/header/226973-1762354305.jpg?lm=1",
    "localImagePath": "public/images/players/fc-fulham/226973.jpg",
    "team": "Fulham FC",
    "teamSlug": "fc-fulham",
    "dateOfBirth": "27/01/1995",
    "age": 30,
    "placeOfBirth": "Worthing",
    "citizenship": [
      "England"
    ],
    "height": "1,81 m",
    "position": "Central Midfield",
    "foot": "right",
    "currentClub": "Fulham FC",
    "joined": "30/08/2020",
    "contractExpires": "30/06/2027",
    "marketValue": "€4.50m",
    "shirtNumber": "6",
    "agent": "Unique Sports Group",
    "internationalTeam": null,
    "internationalCaps": null,
    "internationalGoals": null
  },
  {
    "id": "123275",
    "name": "Tom Cairney Tom Cairney",
    "url": "https://www.transfermarkt.com/tom-cairney/profil/spieler/123275",
    "imageUrl": "https://img.a.transfermarkt.technology/portrait/header/123275-1651652849.jpg?lm=1",
    "localImagePath": "public/images/players/fc-fulham/123275.jpg",
    "team": "Fulham FC",
    "teamSlug": "fc-fulham",
    "dateOfBirth": "20/01/1991",
    "age": 34,
    "placeOfBirth": "Nottingham",
    "citizenship": [
      "Scotland"
    ],
    "height": "1,85 m",
    "position": "Central Midfield",
    "foot": "left",
    "currentClub": "Fulham FC",
    "joined": "01/07/2015",
    "contractExpires": "30/06/2026",
    "marketValue": "€1.00m",
    "shirtNumber": "10",
    "agent": "Unique Sports Group",
    "internationalTeam": null,
    "internationalCaps": null,
    "internationalGoals": null
  },
  {
    "id": "900195",
    "name": "Kevin",
    "url": "https://www.transfermarkt.com/kevin/profil/spieler/900195",
    "imageUrl": "https://img.a.transfermarkt.technology/portrait/header/900195-1762354062.jpg?lm=1",
    "localImagePath": "public/images/players/fc-fulham/900195.jpg",
    "team": "Fulham FC",
    "teamSlug": "fc-fulham",
    "dateOfBirth": "04/01/2003",
    "age": 22,
    "placeOfBirth": "São Paulo",
    "citizenship": [
      "Brazil"
    ],
    "height": "1,76 m",
    "position": "Left Winger",
    "foot": "right",
    "currentClub": "Fulham FC",
    "joined": "01/09/2025",
    "contractExpires": "30/06/2030",
    "marketValue": "€30.00m",
    "shirtNumber": "22",
    "agent": "Talents Sports",
    "internationalTeam": null,
    "internationalCaps": null,
    "internationalGoals": null
  },
  {
    "id": "242631",
    "name": "Alex Iwobi",
    "url": "https://www.transfermarkt.com/alex-iwobi/profil/spieler/242631",
    "imageUrl": "https://img.a.transfermarkt.technology/portrait/header/242631-1679652866.jpg?lm=1",
    "localImagePath": "public/images/players/fc-fulham/242631.jpg",
    "team": "Fulham FC",
    "teamSlug": "fc-fulham",
    "dateOfBirth": "03/05/1996",
    "age": 29,
    "placeOfBirth": "Lagos",
    "citizenship": [
      "Nigeria"
    ],
    "height": "1,83 m",
    "position": "Left Winger",
    "foot": "right",
    "currentClub": "Fulham FC",
    "joined": "01/09/2023",
    "contractExpires": "30/06/2028",
    "marketValue": "€28.00m",
    "shirtNumber": "17",
    "agent": "Elite Project Group",
    "internationalTeam": "Nigeria",
    "internationalCaps": 91,
    "internationalGoals": 10
  },
  {
    "id": "279455",
    "name": "Harry Wilson",
    "url": "https://www.transfermarkt.com/harry-wilson/profil/spieler/279455",
    "imageUrl": "https://img.a.transfermarkt.technology/portrait/header/279455-1668070758.jpg?lm=1",
    "localImagePath": "public/images/players/fc-fulham/279455.jpg",
    "team": "Fulham FC",
    "teamSlug": "fc-fulham",
    "dateOfBirth": "22/03/1997",
    "age": 28,
    "placeOfBirth": "Wrexham",
    "citizenship": [
      "Wales"
    ],
    "height": "1,73 m",
    "position": "Right Winger",
    "foot": "left",
    "currentClub": "Fulham FC",
    "joined": "24/07/2021",
    "contractExpires": "30/06/2026",
    "marketValue": "€18.00m",
    "shirtNumber": "8",
    "agent": "Unique Sports Group",
    "internationalTeam": "Wales",
    "internationalCaps": 67,
    "internationalGoals": 17
  },
  {
    "id": "401922",
    "name": "Samuel Chukwueze",
    "url": "https://www.transfermarkt.com/samuel-chukwueze/profil/spieler/401922",
    "imageUrl": "https://img.a.transfermarkt.technology/portrait/header/401922-1692277617.jpg?lm=1",
    "localImagePath": "public/images/players/fc-fulham/401922.jpg",
    "team": "Fulham FC",
    "teamSlug": "fc-fulham",
    "dateOfBirth": "22/05/1999",
    "age": 26,
    "placeOfBirth": "Umuahia",
    "citizenship": [
      "Nigeria"
    ],
    "height": "1,72 m",
    "position": "Right Winger",
    "foot": "left",
    "currentClub": "Fulham FC",
    "joined": "01/09/2025",
    "contractExpires": "30/06/2026",
    "marketValue": "€10.00m",
    "shirtNumber": "19",
    "agent": "InterLex Sport",
    "internationalTeam": "Nigeria",
    "internationalCaps": 51,
    "internationalGoals": 7
  },
  {
    "id": "204103",
    "name": "Adama Traoré",
    "url": "https://www.transfermarkt.com/adama-traore/profil/spieler/204103",
    "imageUrl": "https://img.a.transfermarkt.technology/portrait/header/204103-1736153427.jpg?lm=1",
    "localImagePath": "public/images/players/fc-fulham/204103.jpg",
    "team": "Fulham FC",
    "teamSlug": "fc-fulham",
    "dateOfBirth": "25/01/1996",
    "age": 29,
    "placeOfBirth": null,
    "citizenship": [
      "Spain"
    ],
    "height": "1,78 m",
    "position": "Right Winger",
    "foot": "right",
    "currentClub": "Fulham FC",
    "joined": "12/08/2023",
    "contractExpires": "30/06/2026",
    "marketValue": "€9.00m",
    "shirtNumber": "11",
    "agent": null,
    "internationalTeam": null,
    "internationalCaps": null,
    "internationalGoals": null
  },
  {
    "id": "735571",
    "name": "Rodrigo Muniz Rodrigo Muniz",
    "url": "https://www.transfermarkt.com/rodrigo-muniz/profil/spieler/735571",
    "imageUrl": "https://img.a.transfermarkt.technology/portrait/header/735571-1657802369.jpg?lm=1",
    "localImagePath": "public/images/players/fc-fulham/735571.jpg",
    "team": "Fulham FC",
    "teamSlug": "fc-fulham",
    "dateOfBirth": "04/05/2001",
    "age": 24,
    "placeOfBirth": null,
    "citizenship": [
      "Brazil"
    ],
    "height": "1,86 m",
    "position": "Centre-Forward",
    "foot": "right",
    "currentClub": "Fulham FC",
    "joined": "20/08/2021",
    "contractExpires": "30/06/2030",
    "marketValue": "€25.00m",
    "shirtNumber": "9",
    "agent": "CAA Base Ltd",
    "internationalTeam": null,
    "internationalCaps": null,
    "internationalGoals": null
  },
  {
    "id": "206040",
    "name": "Raúl Jiménez",
    "url": "https://www.transfermarkt.com/raul-jimenez/profil/spieler/206040",
    "imageUrl": "https://img.a.transfermarkt.technology/portrait/header/206040-1742820547.jpg?lm=1",
    "localImagePath": "public/images/players/fc-fulham/206040.jpg",
    "team": "Fulham FC",
    "teamSlug": "fc-fulham",
    "dateOfBirth": "05/05/1991",
    "age": 34,
    "placeOfBirth": null,
    "citizenship": [
      "Mexico"
    ],
    "height": "1,87 m",
    "position": "Centre-Forward",
    "foot": "right",
    "currentClub": "Fulham FC",
    "joined": "25/07/2023",
    "contractExpires": "30/06/2026",
    "marketValue": "€5.00m",
    "shirtNumber": "7",
    "agent": null,
    "internationalTeam": "Mexico",
    "internationalCaps": 123,
    "internationalGoals": 44
  },
  {
    "id": "1069512",
    "name": "Jonah Kusi-Asare",
    "url": "https://www.transfermarkt.com/jonah-kusi-asare/profil/spieler/1069512",
    "imageUrl": "https://img.a.transfermarkt.technology/portrait/header/1069512-1739808814.jpg?lm=1",
    "localImagePath": "public/images/players/fc-fulham/1069512.jpg",
    "team": "Fulham FC",
    "teamSlug": "fc-fulham",
    "dateOfBirth": "04/07/2007",
    "age": 18,
    "placeOfBirth": "Solna",
    "citizenship": [
      "Sweden"
    ],
    "height": "1,96 m",
    "position": "Centre-Forward",
    "foot": "right",
    "currentClub": "Fulham FC",
    "joined": "01/09/2025",
    "contractExpires": "30/06/2026",
    "marketValue": "€4.00m",
    "shirtNumber": "18",
    "agent": "KSM AGENCY",
    "internationalTeam": null,
    "internationalCaps": null,
    "internationalGoals": null
  }
]